mail_notifier/__init__.py
mail_notifier/mail_notifier.py
mail_notifier-0.0.5.dist-info/METADATA
mail_notifier-0.0.5.dist-info/WHEEL
mail_notifier-0.0.5.dist-info/top_level.txt
mail_notifier-0.0.5.dist-info/RECORD
