Metadata-Version: 2.1
Name: mail-notifier
Version: 0.0.5
Summary: Sending notification via SMTP
Home-page: http://git.shookai.com/team-black/shk-lib-notifier.git
Author: UNKNOWN
Author-email: bartlomiej.tyniewicki@shookai.com
License: UNKNOWN
Platform: UNKNOWN
